[
  {
    "name": "Line Rider",
    "description": "Draw hills and tracks for a sledder to ride on.",
    "link": "https://www.linerider.com/",
    "image": "line-rider.png",
    "dateAdded": "2023-08-12"
  },
  {
    "name": "Townscaper",
    "description": "Build peaceful little island towns.",
    "link": "https://oskarstalberg.com/Townscaper/",
    "image": "townscaper.png",
    "dateAdded": "2023-08-12"
  },
  {
    "name": "The Blob Toy",
    "description": "A physics playground for blobs.",
    "link": "https://oimo.io/works/blob/",
    "image": "the-blob-toy.png",
    "dateAdded": "2023-08-12"
  },
  {
    "name": "PICO-8 Education Edition",
    "description": "A fantasy console for making, sharing, and playing tiny retro games.",
    "link": "https://www.pico-8-edu.com/",
    "image": "pico-8.png",
    "dateAdded": "2023-08-12"
  },
  {
    "name": "Choo Choo World",
    "description": "A 3D wooden train track builder.",
    "link": "https://choochooworld.com/",
    "image": "choo-choo-world.png",
    "dateAdded": "2023-08-12"
  },
  {
    "name": "IsoCity",
    "description": "Build tiny isometric cities from a pallette of simple tiles.",
    "link": "https://victorribeiro.com/isocity/",
    "image": "isocity.png",
    "dateAdded": "2023-08-12"
  },
  {
    "name": "iiisometric",
    "description": "A canvas for drawing with isometric cubes.",
    "link": "https://fffuel.co/iiisometric/",
    "image": "iiisometric.png",
    "dateAdded": "2023-08-12"
  },
  {
    "name": "Shader Toy",
    "description": "A community site for building and sharing shader code creations.",
    "link": "https://www.shadertoy.com/",
    "image": "shader-toy.png",
    "dateAdded": "2023-08-12"
  },
  {
    "name": "Tixy Land",
    "description": "A minimalist creative coding environment inside of a 16x16 grid.",
    "link": "https://tixy.land/",
    "image": "tixy-land.png",
    "dateAdded": "2023-08-12"
  },
  {
    "name": "TLDraw",
    "description": "An online whiteboard and diagramming tool.",
    "link": "https://www.tldraw.com",
    "image": "tldraw.png",
    "dateAdded": "2023-08-12"
  },
  {
    "name": "SumoPaint",
    "description": "An online app for drawing and painting.",
    "link": "https://paint.sumo.app/",
    "image": "sumo-paint.png",
    "dateAdded": "2023-08-12"
  },
  {
    "name": "Slider Land",
    "description": "A creative coding playground using only HTML sliders.",
    "link": "https://sliderland.blinry.org/",
    "image": "sliderland.png",
    "dateAdded": "2023-08-12"
  },
  {
    "name": "KidPix",
    "description": "The classic drawing program designed for kids.",
    "link": "https://kidpix.app/",
    "image": "kid-pix.png",
    "dateAdded": "2023-08-12"
  },
  {
    "name": "make 8-bit art",
    "description": "A lovely online pixel art editor.",
    "link": "https://make8bitart.com/",
    "image": "make-8-bit-art.png",
    "dateAdded": "2023-08-12"
  },
  {
    "name": "Triangulart",
    "description": "Graphic editor for isometric illustrations. Pixel art, but with triangles!",
    "link": "https://maxwellito.github.io/triangulart/",
    "image": "triangulart.png",
    "dateAdded": "2023-08-12"
  },
  {
    "name": "Sandspiel",
    "description": "A falling sand game where you create scenes with elements like sand, water, plant and fire.",
    "link": "https://sandspiel.club/",
    "image": "sandspiel.png",
    "dateAdded": "2023-08-12"
  },
  {
    "name": "Sandspiel Studio",
    "description": "A visual programming tool for creating advanced Sandspiel scenes with custom elements.",
    "link": "https://studio.sandspiel.club/",
    "image": "sandspiel-studio.png",
    "dateAdded": "2023-08-12"
  },
  {
    "name": "Chrome Canvas",
    "description": "A drawing canvas with brushes, markers, and ink.",
    "link": "https://canvas.apps.chrome/",
    "image": "chrome-canvas.png",
    "dateAdded": "2023-08-12"
  },
  {
    "name": "Beepbox",
    "description": "An online tool for sketching and sharing instrumental music.",
    "link": "https://www.beepbox.co/",
    "image": "beepbox.png",
    "dateAdded": "2023-08-12"
  },
  {
    "name": "Music Box Fun",
    "description": "Make and share music box songs online.",
    "link": "https://musicbox.fun/",
    "image": "music-box-fun.png",
    "dateAdded": "2023-08-12"
  },
  {
    "name": "Song Maker",
    "description": "A fun and accessible song making tool by Chrome Music Lab.",
    "link": "https://musiclab.chromeexperiments.com/Song-Maker",
    "image": "song-maker.png",
    "dateAdded": "2023-08-12"
  },
  {
    "name": "Bitsy",
    "description": "An visual editor for making little games or worlds.",
    "link": "https://make.bitsy.org/",
    "image": "bitsy.png",
    "dateAdded": "2023-08-12"
  },
  {
    "name": "PuzzleScript",
    "description": "A simplified code editor for making puzzle games.",
    "link": "https://www.puzzlescript.net/editor.html",
    "image": "puzzle-script.png",
    "dateAdded": "2023-08-12"
  },
  {
    "name": "FlipAnim",
    "description": "Create flipbook animations online.",
    "link": "https://flipanim.com/",
    "image": "flip-anim.png",
    "dateAdded": "2023-08-12"
  },
  {
    "name": "Twine",
    "description": "An online editor for making text-based choose-your-own-adventure stories.",
    "link": "https://twinery.org/",
    "image": "twine.png",
    "dateAdded": "2023-08-12"
  },
  {
    "name": "MakeCode Arcade",
    "description": "A visual programming environment where kids can make games (built by Microsoft).",
    "link": "https://arcade.makecode.com/",
    "image": "makecode-arcade.png",
    "dateAdded": "2023-08-12"
  },
  {
    "name": "Blockbench",
    "description": "A 3D editor for pixel art and low-poly models (including Minecraft).",
    "link": "https://web.blockbench.net/",
    "image": "block-bench.png",
    "dateAdded": "2023-08-12"
  },
  {
    "name": "Mini Music Machine",
    "description": "Polyrhythmic musical loop maker",
    "link": "https://muted.io/mini-music-machine/",
    "image": "mini-music-machine.png",
    "dateAdded": "2023-10-13"
  }
]
